fold_wrappers/__init__.py
fold_wrappers/arch.py
fold_wrappers/convenience.py
fold_wrappers/lightgbm.py
fold_wrappers/neuralforecast.py
fold_wrappers/prophet.py
fold_wrappers/sktime.py
fold_wrappers/statsforecast.py
fold_wrappers/statsmodels.py
fold_wrappers/xgboost.py
fold_wrappers-0.1.2.dist-info/METADATA
fold_wrappers-0.1.2.dist-info/WHEEL
fold_wrappers-0.1.2.dist-info/licenses/LICENSE
fold_wrappers-0.1.2.dist-info/RECORD
