Metadata-Version: 2.1
Name: fold-wrappers
Version: 0.1.2
Summary: 3rd party model wrappers for fold.
Project-URL: Documentation, https://dream-faster.github.io/fold-wrappers
Project-URL: Issues, https://github.com/dream-faster/fold-wrappers/issues
Project-URL: Source, https://github.com/dream-faster/fold-wrappers
Author-email: Mark Aron Szulyovszky <mark@dreamfaster.ai>, Daniel Szemerey <daniel@dreamfaster.ai>
License: MIT License
License-File: LICENSE
Keywords: financial-machine-learning,forecast,forecasting,machine-learning,models,nowcast,time-series,time-series-classification,time-series-regression
Classifier: Development Status :: 5 - Production/Stable
Classifier: License :: Other/Proprietary License
Classifier: Operating System :: OS Independent
Classifier: Programming Language :: Python
Classifier: Programming Language :: Python :: 3.7
Classifier: Programming Language :: Python :: 3.8
Classifier: Programming Language :: Python :: 3.9
Classifier: Programming Language :: Python :: 3.10
Classifier: Programming Language :: Python :: Implementation :: CPython
Classifier: Programming Language :: Python :: Implementation :: PyPy
Requires-Python: >=3.7
Requires-Dist: fold-core~=0.1
Requires-Dist: numpy
Provides-Extra: arch
Requires-Dist: arch>=4.19.0; extra == 'arch'
Provides-Extra: docs
Requires-Dist: mkdocs-autorefs; extra == 'docs'
Requires-Dist: mkdocs-include-markdown-plugin; extra == 'docs'
Requires-Dist: mkdocs-material; extra == 'docs'
Requires-Dist: mkdocstrings-python; extra == 'docs'
Provides-Extra: lightgbm
Requires-Dist: lightgbm; extra == 'lightgbm'
Provides-Extra: neuralforecast
Requires-Dist: neuralforecast>=1.4; extra == 'neuralforecast'
Requires-Dist: torch<2.0.0; extra == 'neuralforecast'
Provides-Extra: prophet
Requires-Dist: prophet; extra == 'prophet'
Provides-Extra: quality
Requires-Dist: black~=22.10.0; extra == 'quality'
Requires-Dist: flake8~=4.0.1; extra == 'quality'
Requires-Dist: isort~=5.10.1; extra == 'quality'
Requires-Dist: pre-commit~=2.20.0; extra == 'quality'
Provides-Extra: sktime
Requires-Dist: pmdarima>=2.0.0; extra == 'sktime'
Requires-Dist: sktime>=0.16.0; extra == 'sktime'
Provides-Extra: statsforecast
Requires-Dist: statsforecast>=1.5; extra == 'statsforecast'
Provides-Extra: statsmodels
Requires-Dist: statsmodels>=0.12.0; extra == 'statsmodels'
Provides-Extra: tests
Requires-Dist: fold-core~=0.1; extra == 'tests'
Requires-Dist: pytest~=7.1.2; extra == 'tests'
Provides-Extra: xgboost
Requires-Dist: xgboost; extra == 'xgboost'
